livy_uploads/__init__.py
livy_uploads/auth.py
livy_uploads/commands.py
livy_uploads/endpoint.py
livy_uploads/exceptions.py
livy_uploads/hostinfo.ipynb
livy_uploads/logs.py
livy_uploads/magics.py
livy_uploads/pack.py
livy_uploads/paths.py
livy_uploads/retry_policy.py
livy_uploads/session.py
livy_uploads/utils.py
livy_uploads/spark/hostinfo.ipynb
livy_uploads/spark/session-info.ipynb
livy_uploads-0.1.5.dist-info/METADATA
livy_uploads-0.1.5.dist-info/WHEEL
livy_uploads-0.1.5.dist-info/licenses/LICENSE
livy_uploads-0.1.5.dist-info/RECORD
