Metadata-Version: 2.4
Name: livy-uploads
Version: 0.1.5
Summary: Upload files and arbitrary objects to Livy
Author-email: Diógenes Oliveira <diogenes1oliveira@gmail.com>
License: MIT License
License-File: LICENSE
Requires-Python: >=3.9
Requires-Dist: python-dotenv>=1.2.1
Requires-Dist: requests-toolbelt>=1.0.0
Requires-Dist: requests>=2.32.5
